jak/__init__.py
jak/aes_cipher.py
jak/app.py
jak/compat.py
jak/crypto_services.py
jak/decorators.py
jak/diff.py
jak/exceptions.py
jak/helpers.py
jak/outputs.py
jak/padding.py
jak/start.py
jak-0.14.6.dist-info/LICENSE
jak-0.14.6.dist-info/LICENSE.txt
jak-0.14.6.dist-info/METADATA
jak-0.14.6.dist-info/WHEEL
jak-0.14.6.dist-info/entry_points.txt
jak-0.14.6.dist-info/top_level.txt
jak-0.14.6.dist-info/RECORD
