Metadata-Version: 2.1
Name: jak
Version: 0.14.6
Summary: jak makes encrypting files really easy
Home-page: https://github.com/dispel/jak
Author: Dispel, LLC
Author-email: jak@dispel.io
License: Apache-2.0
Platform: any
Classifier: Development Status :: 4 - Beta
Classifier: Environment :: Console
Classifier: Intended Audience :: Developers
Classifier: License :: OSI Approved :: Apache Software License
Classifier: Natural Language :: English
Classifier: Operating System :: POSIX
Classifier: Operating System :: MacOS
Classifier: Operating System :: Unix
Classifier: Programming Language :: Python
Classifier: Programming Language :: Python :: 2.7
Classifier: Programming Language :: Python :: 3.4
Classifier: Programming Language :: Python :: 3.5
Classifier: Programming Language :: Python :: 3.6
Classifier: Programming Language :: Python :: Implementation :: PyPy
Requires-Dist: click (>=6.6)
Requires-Dist: pycrypto (>=2.6.1)
Requires-Dist: six (>=1.10.0)
